<Objects>
    <Object>
        <id>SmartHouse</id>
        <Object>
            <id>BedRoom</id>
            <InfoItem name="Moisture">
                <value unixTime="1479805133" dateTime="2016-11-22T09:58:53.425+01:00" type="xs:double">-1.0</value>
            </InfoItem>
        </Object>
        <Object>
            <id>Kitchen</id>
            <InfoItem name="Moisture">
                <description>
                </description>
                <MetaData>
                    <InfoItem name="Accuracy">
                        <value unixTime="1479724613" dateTime="2016-11-21T11:36:53.364+01:00" type="xs:double">0.5</value>
                    </InfoItem>
                    <InfoItem name="Latency">
                        <value unixTime="1479724613" dateTime="2016-11-21T11:36:53.364+01:00" type="xs:double">2.3</value>
                    </InfoItem>
                </MetaData>
                <value unixTime="1479805133" dateTime="2016-11-22T09:58:53.425+01:00" type="xs:double">0.0</value>
            </InfoItem>
        </Object>
    </Object>
</Objects>


<http://eis-biotope.iais.fraunhofer.de/biotope.sntiotlab.lu/SmartHouse> a odf:Object;
        skos:notation "SmartHouse";
        odf:object [
        skos:notation "Kitchen";
        odf:infoitem [
        a odf:InfoItem;
        dcterms:title "Moisture";
        dcterms:description "";
        odf:metadata [
        odf:infoitem [
        dcterms:title "Accuracy";
        odf:value [
        dcterms:created "2016-11-21T11:36:53.364+01:00"^^xsd:dateTime;
        odf:dataValue 0.5^^xsd:double
        ]
        ]
        odf:infoitem [
        dcterms:title "Latency";
        odf:value [
        dcterms:created "2016-11-21T11:36:53.364+01:00"^^xsd:dateTime;
        odf:dataValue 2.3^^xsd:double
        ]
        ]
        ]
        odf:value [
        dcterms:created "016-11-22T09:48:15.946+01:00"^^xsd:dateTime;
        odf:dataValue "metadata to be added"^^xsd:String
        ]
        ]